resident_portal/__init__.py
resident_portal/exceptions.py
resident_portal/lease.py
resident_portal/models.py
resident_portal/session.py
resident_portal/user.py
resident_portal-0.0.1.dist-info/licenses/LICENSE
resident_portal-0.0.1.dist-info/METADATA
resident_portal-0.0.1.dist-info/WHEEL
resident_portal-0.0.1.dist-info/top_level.txt
resident_portal-0.0.1.dist-info/RECORD
